abx_plugin_default_binproviders.py
abx_plugin_default_binproviders-2024.10.24.dist-info/METADATA
abx_plugin_default_binproviders-2024.10.24.dist-info/WHEEL
abx_plugin_default_binproviders-2024.10.24.dist-info/entry_points.txt
abx_plugin_default_binproviders-2024.10.24.dist-info/RECORD
