Metadata-Version: 2.4
Name: abx-plugin-default-binproviders
Version: 2024.10.24
Summary: Default BinProviders for ABX (apt, brew, env)
Requires-Python: >=3.10
Requires-Dist: abx-pkg>=0.5.4
Requires-Dist: abx-spec-abx-pkg>=0.1.0
Requires-Dist: abx>=0.1.0
